pysimplese/__init__.py
pysimplese/download.py
pysimplese/load.py
pysimplese/run.py
pysimplese/clitools/__init__.py
pysimplese/clitools/cli.py
pysimplese/search/__init__.py
pysimplese/search/analysis.py
pysimplese/search/documents.py
pysimplese/search/index.py
pysimplese/search/timing.py
pysimplese-0.0.0.1.dist-info/LICENSE
pysimplese-0.0.0.1.dist-info/METADATA
pysimplese-0.0.0.1.dist-info/WHEEL
pysimplese-0.0.0.1.dist-info/entry_points.txt
pysimplese-0.0.0.1.dist-info/top_level.txt
pysimplese-0.0.0.1.dist-info/RECORD
